MANIFEST.in
setup.py
pyvod.pluzz.egg-info/PKG-INFO
pyvod.pluzz.egg-info/SOURCES.txt
pyvod.pluzz.egg-info/dependency_links.txt
pyvod.pluzz.egg-info/entry_points.txt
pyvod.pluzz.egg-info/not-zip-safe
pyvod.pluzz.egg-info/requires.txt
pyvod.pluzz.egg-info/top_level.txt
vod/pluzz/__init__.py
vod/pluzz/pluzz.py