Metadata-Version: 1.1
Name: pyvod.pluzz
Version: 1.5
Summary: PyVOD pluzz browser
Home-page: http://m0g.net
Author: Bernard `Guyzmo` Pratz
Author-email: pypluzz@m0g.net
License: GPLv3
Keywords: download tv show
Platform: UNKNOWN
Classifier: Development Status :: 4 - Beta
Classifier: License :: OSI Approved
Classifier: Operating System :: Unix
